argus_enterprise_api/__init__.py
argus_enterprise_api/api/__init__.py
argus_enterprise_api/api/argus_client.py
argus_enterprise_api/api/blueprints.py
argus_enterprise_api/api/utils.py
argus_enterprise_api/api/spec/ModelManagementApi-3_0-swagger.json
argus_enterprise_api/api/spec/ModelManagementApi-4_0-swagger.json
argus_enterprise_api/api/spec/ModelManagementApi-5_0-swagger.json
argus_enterprise_api/api/spec/WorkspaceApi-3_0-swagger.json
argus_enterprise_api/api/spec/WorkspaceApi-4_0-swagger.json
argus_enterprise_api/api/spec/WorkspaceApi-5_0-swagger.json
argus_enterprise_api-1.0.7.dist-info/LICENSE
argus_enterprise_api-1.0.7.dist-info/METADATA
argus_enterprise_api-1.0.7.dist-info/WHEEL
argus_enterprise_api-1.0.7.dist-info/top_level.txt
argus_enterprise_api-1.0.7.dist-info/RECORD
