Metadata-Version: 2.1
Name: argus-enterprise-api
Version: 1.0.7
Summary: A Python SDK for interacting with the Argus Enterprise API
Home-page: https://github.com/budaesandrei/argus-enterprise-api
Author: Andrei Budaes-Tanaru
Author-email: budaesandrei@gmail.com
Classifier: Programming Language :: Python :: 3
Classifier: License :: OSI Approved :: MIT License
Classifier: Operating System :: OS Independent
Classifier: Intended Audience :: Developers
Classifier: Topic :: Software Development :: Build Tools
Classifier: Topic :: Software Development :: Libraries :: Python Modules
Classifier: Development Status :: 5 - Production/Stable
Requires-Python: >=3.9
License-File: LICENSE
Requires-Dist: cryptography <42.0.0,>=41.0.4
Requires-Dist: PyJWT <3.0.0,>=2.8.0
Requires-Dist: requests <3.0.0,>=2.31.0
Requires-Dist: setuptools <59.0.0,>=58.1.0
